hello/__init__.py
hello/hello.py
susilpkg-0.0.1.dist-info/METADATA
susilpkg-0.0.1.dist-info/WHEEL
susilpkg-0.0.1.dist-info/top_level.txt
susilpkg-0.0.1.dist-info/RECORD
