Metadata-Version: 2.1
Name: susilpkg
Version: 0.0.1
Summary: A basic hello package.
Home-page: UNKNOWN
Author: susilthapa (Susil Thapa)
Author-email: <thapasusil53@gmail.com>
License: UNKNOWN
Keywords: python,hello
Platform: UNKNOWN
Classifier: Development Status :: 1 - Planning
Classifier: Intended Audience :: Developers
Classifier: Programming Language :: Python :: 3
Classifier: Operating System :: Unix
Classifier: Operating System :: MacOS :: MacOS X
Classifier: Operating System :: Microsoft :: Windows
